travelkml/__init__.py
travelkml/skeleton.py
travelkml-0.0.post1.dev2.dist-info/LICENSE.txt
travelkml-0.0.post1.dev2.dist-info/METADATA
travelkml-0.0.post1.dev2.dist-info/WHEEL
travelkml-0.0.post1.dev2.dist-info/top_level.txt
travelkml-0.0.post1.dev2.dist-info/RECORD
