Metadata-Version: 2.1
Name: travelkml
Version: 0.0.post1.dev2
Summary: Add a short description here!
Home-page: https://github.com/pyscaffold/pyscaffold/
Author: Sean Koenig
Author-email: 56701039+DataCascadia@users.noreply.github.com
License: MIT
Project-URL: Documentation, https://pyscaffold.org/
Platform: any
Classifier: Development Status :: 4 - Beta
Classifier: Programming Language :: Python
License-File: LICENSE.txt
Requires-Dist: importlib-metadata ; python_version < "3.8"
Provides-Extra: testing
Requires-Dist: setuptools ; extra == 'testing'
Requires-Dist: pytest ; extra == 'testing'
Requires-Dist: pytest-cov ; extra == 'testing'
